selext/__init__.py
selext/webdriver.py
selext-0.2.1.dist-info/LICENSE
selext-0.2.1.dist-info/WHEEL
selext-0.2.1.dist-info/METADATA
selext-0.2.1.dist-info/RECORD
